dash_cognito_auth/__init__.py
dash_cognito_auth/auth.py
dash_cognito_auth/cognito.py
dash_cognito_auth/cognito_oauth.py
dash_cognito_auth-0.0.5.dist-info/LICENSE.md
dash_cognito_auth-0.0.5.dist-info/METADATA
dash_cognito_auth-0.0.5.dist-info/WHEEL
dash_cognito_auth-0.0.5.dist-info/top_level.txt
dash_cognito_auth-0.0.5.dist-info/RECORD
