Metadata-Version: 2.1
Name: dash-cognito-auth
Version: 0.0.5
Summary: Dash Cognito Auth
Home-page: https://github.com/fspijkerman/dash-cognito-auth
Author: Frank Spijkerman
Author-email: frank@jeito.nl
License: MIT
Classifier: License :: OSI Approved :: MIT License
Classifier: Programming Language :: Python
Classifier: Programming Language :: Python :: Implementation :: CPython
Requires-Python: >=3.10
License-File: LICENSE.md
Requires-Dist: dash >=0.41.0
Requires-Dist: dash-core-components >=0.46.0
Requires-Dist: dash-html-components >=0.15.0
Requires-Dist: Flask >=1.0.2
Requires-Dist: Flask-Dance >=1.2.0
Requires-Dist: six >=1.11.0
